WhatPulse_API/__init__.py
WhatPulse_API_Py-0.3.0.dist-info/LICENSE
WhatPulse_API_Py-0.3.0.dist-info/METADATA
WhatPulse_API_Py-0.3.0.dist-info/WHEEL
WhatPulse_API_Py-0.3.0.dist-info/top_level.txt
WhatPulse_API_Py-0.3.0.dist-info/RECORD
