Metadata-Version: 2.1
Name: WhatPulse-API-Py
Version: 0.3.0
Summary: Easy Module to work with WhatPulse Client API.
Author: Flörian
Author-email: iaccidentlyatekerosin@gmail.com
License: GNU General Public License v3.0 or later
Keywords: WhatPulse
Classifier: License :: OSI Approved :: GNU General Public License v3 or later (GPLv3+)
Classifier: Programming Language :: Python :: 3.8
Classifier: Programming Language :: Python :: 3.9
Classifier: Programming Language :: Python :: 3.10
Classifier: Programming Language :: Python :: 3.11
Classifier: Programming Language :: Python :: 3.12
License-File: LICENSE
